{"cameraMode":{"drawMode":0,"name":"Shaded","section":"Shading Mode"},"sceneLighting":true,"audioPlay":false,"sceneViewState":{"showFog":true,"showMaterialUpdate":false,"showSkybox":true,"showFlares":true,"showImageEffects":true,"showParticleSystems":true},"in2DMode":false,"pivot":{"x":-76.41206359863281,"y":1.7651450634002686,"z":-1.4957187175750733},"rotation":{"x":0.1065976694226265,"y":0.7199211120605469,"z":-0.11343476176261902,"w":0.6763750314712524},"size":3.457883834838867,"orthographic":false}